{"color": "Color", "director_name": "Peter Jackson", "num_voted_users": "354228", "duration": "164", "actor_3_facebook_likes": "773", "actor_2_name": "Adam Brown", "actor_1_facebook_likes": "5000", "gross": "255108370", "genres": "Adventure|Fantasy", "actor_1_name": "Aidan Turner", "description": "Bilbo and Company are forced to engage in a war against an array of combatants and keep the Lonely Mountain from falling into the hands of a rising darkness.", "movie_title": "The Hobbit: The Battle of the Five Armies ", "image_url": "https://images-na.ssl-images-amazon.com/images/M/MV5BODAzMDgxMDc1MF5BMl5BanBnXkFtZTgwMTI0OTAzMjE@._V1_UX182_CR0,0,182,268_AL_.jpg", "num_critic_for_reviews": "422", "director_facebook_likes": "0", "actor_3_name": "James Nesbitt", "facenumber_in_poster": "0", "plot_keywords": "army|elf|hobbit|middle earth|orc", "movie_imdb_link": "http://www.imdb.com/title/tt2310332/?ref_=fn_tt_tt_1", "num_user_for_reviews": "802", "language": "English", "country": "New Zealand", "content_rating": "PG-13", "cast_total_facebook_likes": "9152", "budget": "250000000", "title_year": "2014", "actor_2_facebook_likes": "972", "imdb_score": "7.5", "aspect_ratio": "2.35", "movie_facebook_likes": "65000", "trailer_url": "http://www.imdb.com/video/imdb/vi1092005657?playlistId=tt2310332&ref_=tt_ov_vi"}