{"color": "Color", "director_name": "James Bobin", "num_voted_users": "21352", "duration": "113", "actor_3_facebook_likes": "11000", "actor_2_name": "Alan Rickman", "actor_1_facebook_likes": "40000", "gross": "76846624", "genres": "Adventure|Family|Fantasy", "actor_1_name": "Johnny Depp", "description": "Alice returns to the whimsical world of Wonderland and travels back in time to help the Mad Hatter.", "movie_title": "Alice Through the Looking Glass ", "image_url": "https://images-na.ssl-images-amazon.com/images/M/MV5BMTc2NjExMTIyN15BMl5BanBnXkFtZTgwMjg0OTIwODE@._V1_UX182_CR0,0,182,268_AL_.jpg", "num_critic_for_reviews": "218", "director_facebook_likes": "33", "actor_3_name": "Anne Hathaway", "facenumber_in_poster": "1", "plot_keywords": "clock|dark fantasy|mad hatter|queen|sequel", "movie_imdb_link": "http://www.imdb.com/title/tt2567026/?ref_=fn_tt_tt_1", "num_user_for_reviews": "131", "language": "English", "country": "USA", "content_rating": "PG", "cast_total_facebook_likes": "80806", "budget": "170000000", "title_year": "2016", "actor_2_facebook_likes": "25000", "imdb_score": "6.4", "aspect_ratio": "1.85", "movie_facebook_likes": "30000", "trailer_url": "http://www.imdb.com/video/imdb/vi2708190489?playlistId=tt2567026&ref_=tt_ov_vi"}