{"color": "Color", "director_name": "Ash Brannon", "num_voted_users": "54077", "duration": "85", "actor_3_facebook_likes": "970", "actor_2_name": "Zooey Deschanel", "actor_1_facebook_likes": "12000", "gross": "58867694", "genres": "Animation|Comedy|Family|Sport", "actor_1_name": "Jeff Bridges", "description": "A behind-the-scenes look at the annual Penguin World Surfing Championship, and its newest participant, up-and-comer Cody Maverick.", "movie_title": "Surf's Up ", "image_url": "https://images-na.ssl-images-amazon.com/images/M/MV5BMjE4NDE3NzcwM15BMl5BanBnXkFtZTcwMTI0ODYzMw@@._V1_UX182_CR0,0,182,268_AL_.jpg", "num_critic_for_reviews": "154", "director_facebook_likes": "9", "actor_3_name": "Jon Heder", "facenumber_in_poster": "0", "plot_keywords": "chicken|competition|island|penguin|surfing", "movie_imdb_link": "http://www.imdb.com/title/tt0423294/?ref_=fn_tt_tt_1", "num_user_for_reviews": "112", "language": "English", "country": "USA", "content_rating": "PG", "cast_total_facebook_likes": "25590", "budget": "100000000", "title_year": "2007", "actor_2_facebook_likes": "11000", "imdb_score": "6.8", "aspect_ratio": "1.85", "movie_facebook_likes": "0", "trailer_url": "http://www.imdb.com/title/tt0423294/videoplayer/vi4186702105?ref_=tt_pv_vi_aiv_2"}