{"color": "Color", "director_name": "Justin Lin", "num_voted_users": "53607", "duration": "122", "actor_3_facebook_likes": "105", "actor_2_name": "Melissa Roxburgh", "actor_1_facebook_likes": "998", "gross": "130468626", "genres": "Action|Adventure|Sci-Fi|Thriller", "actor_1_name": "Sofia Boutella", "description": "The U.S.S. Enterprise crew explores the furthest reaches of uncharted space, where they encounter a new ruthless enemy, who puts them, and everything the Federation stands for, to the test.", "movie_title": "Star Trek Beyond ", "image_url": "https://images-na.ssl-images-amazon.com/images/M/MV5BZDRiOGE5ZTctOWIxOS00MWQwLThlMDYtNWIwMDQwNzBjZDY1XkEyXkFqcGdeQXVyNjU0OTQ0OTY@._V1_UX182_CR0,0,182,268_AL_.jpg", "num_critic_for_reviews": "322", "director_facebook_likes": "681", "actor_3_name": "Lydia Wilson", "facenumber_in_poster": "4", "plot_keywords": "hatred|sequel|space opera|star trek|third part", "movie_imdb_link": "http://www.imdb.com/title/tt2660888/?ref_=fn_tt_tt_1", "num_user_for_reviews": "432", "language": "English", "country": "USA", "content_rating": "PG-13", "cast_total_facebook_likes": "1327", "budget": "185000000", "title_year": "2016", "actor_2_facebook_likes": "119", "imdb_score": "7.5", "aspect_ratio": "2.35", "movie_facebook_likes": "30000", "trailer_url": "http://www.imdb.com/video/imdb/vi354465561?playlistId=tt2660888&ref_=tt_ov_vi"}